rustworkx_utils/__init__.py
rustworkx_utils/graph_visualizer.py
rustworkx_utils/rxnode.py
rustworkx_utils/utils.py
rustworkx_utils-0.0.1.dist-info/licenses/LICENSE
rustworkx_utils-0.0.1.dist-info/METADATA
rustworkx_utils-0.0.1.dist-info/WHEEL
rustworkx_utils-0.0.1.dist-info/top_level.txt
rustworkx_utils-0.0.1.dist-info/RECORD
