Metadata-Version: 2.4
Name: rustworkx_utils
Version: 0.0.1
Summary: Provides utils for for graphs constructed with rustworkx
Author-email: Abdelrhman Bassiouny <abassiou@uni-bremen.de>
License:                     GNU GENERAL PUBLIC LICENSE
Project-URL: Homepage, https://github.com/AbdelrhmanBassiouny/rustworkx_utils
Keywords: rustworkx,graphs,utils,visualization
Classifier: Programming Language :: Python :: 3
License-File: LICENSE
Requires-Dist: rustworkx
Requires-Dist: matplotlib
Requires-Dist: igraph
Requires-Dist: typing_extensions
Dynamic: license-file
